wmu_greek_utils/__init__.py
wmu_greek_utils/agdt.py
wmu_greek_utils/normalize.py
wmu_greek_utils-0.3.1.dist-info/LICENSE
wmu_greek_utils-0.3.1.dist-info/METADATA
wmu_greek_utils-0.3.1.dist-info/WHEEL
wmu_greek_utils-0.3.1.dist-info/RECORD
