Metadata-Version: 2.1
Name: wmu-greek-utils
Version: 0.3.1
Summary: A collection of utilities for working with Greek text
Author: Will Fitzgerald
Author-email: willf@users.noreply.github.com
Requires-Python: >=3.8.1
Classifier: Programming Language :: Python :: 3
Classifier: Programming Language :: Python :: 3.9
Classifier: Programming Language :: Python :: 3.10
Classifier: Programming Language :: Python :: 3.11
Classifier: Programming Language :: Python :: 3.12
Requires-Dist: greek-normalisation (>=0.5.1,<0.6.0)
Requires-Dist: python-dotenv (>=1.0.1,<2.0.0)
Requires-Dist: regex (>=2024.7.24,<2025.0.0)
